codergpt/__init__.py
codergpt/cli.py
codergpt/commenter/__init__.py
codergpt/commenter/commenter.py
codergpt/constants.py
codergpt/documenter/__init__.py
codergpt/documenter/documenter.py
codergpt/explainer/__init__.py
codergpt/explainer/explainer.py
codergpt/extensions.yaml
codergpt/main.py
codergpt/optimizer/__init__.py
codergpt/optimizer/optimizer.py
codergpt/templates/python_code_comments.md
codergpt/templates/sphinx_style_document.md
codergpt/test_writer/__init__.py
codergpt/test_writer/test_writer.py
codergpt-0.1.8.dist-info/LICENSE
codergpt-0.1.8.dist-info/METADATA
codergpt-0.1.8.dist-info/WHEEL
codergpt-0.1.8.dist-info/entry_points.txt
codergpt-0.1.8.dist-info/RECORD
