Metadata-Version: 2.1
Name: CoderGPT
Version: 0.1.8
Summary: CoderGPT
License: MIT
Author: Harshad Hegde
Author-email: hhegde@lbl.gov
Requires-Python: >=3.9,<4.0
Classifier: License :: OSI Approved :: MIT License
Classifier: Programming Language :: Python :: 3
Classifier: Programming Language :: Python :: 3.9
Classifier: Programming Language :: Python :: 3.10
Classifier: Programming Language :: Python :: 3.11
Classifier: Programming Language :: Python :: 3.12
Requires-Dist: click
Requires-Dist: importlib-metadata (>=4.8.0)
Requires-Dist: langchain (>=0.1.6,<0.2.0)
Requires-Dist: langchain-google-genai (>=0.0.8,<0.0.9)
Requires-Dist: langchain-openai (>=0.0.5,<0.0.6)
Requires-Dist: poetry-dynamic-versioning (>=1.2.0,<2.0.0)
Requires-Dist: tabulate (>=0.9.0,<0.10.0)
